{
  "stamp": "20260713T104425Z",
  "tick": 159,
  "venue": "A800_scientist_v0.1",
  "train_steps": 500,
  "hf_set": true,
  "token_set": true,
  "mode": "calm_longrun",
  "clean": true,
  "host": "klab",
  "nvidia_smi": "GPU 0: NVIDIA A800-SXM4-80GB (UUID: GPU-3df8ec45-ea04-9bde-3b6c-5c85409e9372)",
  "torch": "2.6.0+cu124",
  "cuda": true,
  "gpu_name": "NVIDIA A800-SXM4-80GB",
  "resumed_from": "/home/mw/project/NEXUS_session4/checkpoints/tinylm_a800_t158_20260713T104238Z.pt",
  "train": {
    "sec": 0.501,
    "steps": 500,
    "loss_curve": [
      8.3184175491333,
      8.405021667480469,
      8.398079872131348,
      8.512666702270508,
      8.447078704833984,
      8.41062068939209,
      8.420628547668457,
      8.353107452392578,
      8.318519592285156,
      8.551849365234375,
      8.440014839172363
    ],
    "device": "cuda"
  },
  "ckpt": "/home/mw/project/NEXUS_session4/checkpoints/tinylm_a800_t159_20260713T104425Z.pt",
  "ckpt_kept": 2
}