{
  "stamp": "20260713T013405Z",
  "tick": 265,
  "venue": "A800_scientist_v0.1",
  "train_steps": 500,
  "hf_set": true,
  "token_set": true,
  "mode": "calm_longrun",
  "clean": true,
  "host": "klab",
  "nvidia_smi": "GPU 0: NVIDIA A800-SXM4-80GB (UUID: GPU-3df8ec45-ea04-9bde-3b6c-5c85409e9372)",
  "torch": "2.6.0+cu124",
  "cuda": true,
  "gpu_name": "NVIDIA A800-SXM4-80GB",
  "resumed_from": "/home/mw/project/NEXUS_session4/checkpoints/tinylm_a800_t264_20260713T013216Z.pt",
  "train": {
    "sec": 0.518,
    "steps": 500,
    "loss_curve": [
      8.578396797180176,
      8.272061347961426,
      8.435850143432617,
      8.409770011901855,
      8.436293601989746,
      8.416186332702637,
      8.310660362243652,
      8.392156600952148,
      8.440634727478027,
      8.44605827331543,
      8.515368461608887
    ],
    "device": "cuda"
  },
  "ckpt": "/home/mw/project/NEXUS_session4/checkpoints/tinylm_a800_t265_20260713T013405Z.pt",
  "ckpt_kept": 2,
  "gh_upload": "5ce4a2c"
}